{
    "course_home": {},
    "bbb_session": {
        "url": "https://auladigital.sence.cl/mod/bigbluebuttonbn/view.php?id=748489",
        "title": "Aula virtual en vivo M贸dulo 2",
        "recordings": [
            {
                "name": "Presentation\nAula virtual en vivo M贸dulo 2  Acceso a clases sincr贸nicasTe acercamos el enlace que utilizar...\nHover over an image to view it in full size\nMon, 5 Jan 2026, 5:50 PM -03 75",
                "type": "Presentation",
                "playback_link": "https://auladigital.sence.cl/mod/bigbluebuttonbn/bbb_view.php?action=play&bn=74528&mid=a268278243f16245a9538681a3a3ffdf76dfdcc4-5967-74528&rid=86cbb5c36361c9471658fc29134a603ab1b0ad30-1767646200903&rtype=presentation&href=https%3A%2F%2Faulavirtual.sence.cl%2Fplayback%2Fpresentation%2F2.3%2F86cbb5c36361c9471658fc29134a603ab1b0ad30-1767646200903"
            },
            {
                "name": "Presentation\nAula virtual en vivo M贸dulo 2  Acceso a clases sincr贸nicasTe acercamos el enlace que utilizar...\nHover over an image to view it in full size\nMon, 5 Jan 2026, 7:18 PM -03 49",
                "type": "Presentation",
                "playback_link": "https://auladigital.sence.cl/mod/bigbluebuttonbn/bbb_view.php?action=play&bn=74528&mid=a268278243f16245a9538681a3a3ffdf76dfdcc4-5967-74528&rid=86cbb5c36361c9471658fc29134a603ab1b0ad30-1767651489874&rtype=presentation&href=https%3A%2F%2Faulavirtual.sence.cl%2Fplayback%2Fpresentation%2F2.3%2F86cbb5c36361c9471658fc29134a603ab1b0ad30-1767651489874"
            },
            {
                "name": "Presentation\nAula virtual en vivo M贸dulo 2  Acceso a clases sincr贸nicasTe acercamos el enlace que utilizar...\nHover over an image to view it in full size\nMon, 5 Jan 2026, 8:17 PM -03 107",
                "type": "Presentation",
                "playback_link": "https://auladigital.sence.cl/mod/bigbluebuttonbn/bbb_view.php?action=play&bn=74528&mid=a268278243f16245a9538681a3a3ffdf76dfdcc4-5967-74528&rid=86cbb5c36361c9471658fc29134a603ab1b0ad30-1767655030575&rtype=presentation&href=https%3A%2F%2Faulavirtual.sence.cl%2Fplayback%2Fpresentation%2F2.3%2F86cbb5c36361c9471658fc29134a603ab1b0ad30-1767655030575"
            },
            {
                "name": "Presentation\nAula virtual en vivo M贸dulo 2  Acceso a clases sincr贸nicasTe acercamos el enlace que utilizar...\nHover over an image to view it in full size\nTue, 6 Jan 2026, 5:52 PM -03 69",
                "type": "Presentation",
                "playback_link": "https://auladigital.sence.cl/mod/bigbluebuttonbn/bbb_view.php?action=play&bn=74528&mid=a268278243f16245a9538681a3a3ffdf76dfdcc4-5967-74528&rid=86cbb5c36361c9471658fc29134a603ab1b0ad30-1767732755528&rtype=presentation&href=https%3A%2F%2Faulavirtual.sence.cl%2Fplayback%2Fpresentation%2F2.3%2F86cbb5c36361c9471658fc29134a603ab1b0ad30-1767732755528"
            },
            {
                "name": "Presentation\nAula virtual en vivo M贸dulo 2  Acceso a clases sincr贸nicasTe acercamos el enlace que utilizar...\nHover over an image to view it in full size\nTue, 6 Jan 2026, 7:05 PM -03 63",
                "type": "Presentation",
                "playback_link": "https://auladigital.sence.cl/mod/bigbluebuttonbn/bbb_view.php?action=play&bn=74528&mid=a268278243f16245a9538681a3a3ffdf76dfdcc4-5967-74528&rid=86cbb5c36361c9471658fc29134a603ab1b0ad30-1767737150474&rtype=presentation&href=https%3A%2F%2Faulavirtual.sence.cl%2Fplayback%2Fpresentation%2F2.3%2F86cbb5c36361c9471658fc29134a603ab1b0ad30-1767737150474"
            },
            {
                "name": "Presentation\nAula virtual en vivo M贸dulo 2  Acceso a clases sincr贸nicasTe acercamos el enlace que utilizar...\nHover over an image to view it in full size\nTue, 6 Jan 2026, 8:12 PM -03 53",
                "type": "Presentation",
                "playback_link": "https://auladigital.sence.cl/mod/bigbluebuttonbn/bbb_view.php?action=play&bn=74528&mid=a268278243f16245a9538681a3a3ffdf76dfdcc4-5967-74528&rid=86cbb5c36361c9471658fc29134a603ab1b0ad30-1767741142144&rtype=presentation&href=https%3A%2F%2Faulavirtual.sence.cl%2Fplayback%2Fpresentation%2F2.3%2F86cbb5c36361c9471658fc29134a603ab1b0ad30-1767741142144"
            },
            {
                "name": "Presentation\nAula virtual en vivo M贸dulo 2  Acceso a clases sincr贸nicasTe acercamos el enlace que utilizar...\nHover over an image to view it in full size\nTue, 6 Jan 2026, 9:08 PM -03 38",
                "type": "Presentation",
                "playback_link": "https://auladigital.sence.cl/mod/bigbluebuttonbn/bbb_view.php?action=play&bn=74528&mid=a268278243f16245a9538681a3a3ffdf76dfdcc4-5967-74528&rid=86cbb5c36361c9471658fc29134a603ab1b0ad30-1767744493850&rtype=presentation&href=https%3A%2F%2Faulavirtual.sence.cl%2Fplayback%2Fpresentation%2F2.3%2F86cbb5c36361c9471658fc29134a603ab1b0ad30-1767744493850"
            },
            {
                "name": "Presentation\nAula virtual en vivo M贸dulo 2  Acceso a clases sincr贸nicasTe acercamos el enlace que utilizar...\nHover over an image to view it in full size\nWed, 7 Jan 2026, 5:52 PM -03 77",
                "type": "Presentation",
                "playback_link": "https://auladigital.sence.cl/mod/bigbluebuttonbn/bbb_view.php?action=play&bn=74528&mid=a268278243f16245a9538681a3a3ffdf76dfdcc4-5967-74528&rid=86cbb5c36361c9471658fc29134a603ab1b0ad30-1767819140843&rtype=presentation&href=https%3A%2F%2Faulavirtual.sence.cl%2Fplayback%2Fpresentation%2F2.3%2F86cbb5c36361c9471658fc29134a603ab1b0ad30-1767819140843"
            },
            {
                "name": "Presentation\nAula virtual en vivo M贸dulo 2  Acceso a clases sincr贸nicasTe acercamos el enlace que utilizar...\nHover over an image to view it in full size\nWed, 7 Jan 2026, 7:14 PM -03 53",
                "type": "Presentation",
                "playback_link": "https://auladigital.sence.cl/mod/bigbluebuttonbn/bbb_view.php?action=play&bn=74528&mid=a268278243f16245a9538681a3a3ffdf76dfdcc4-5967-74528&rid=86cbb5c36361c9471658fc29134a603ab1b0ad30-1767824062525&rtype=presentation&href=https%3A%2F%2Faulavirtual.sence.cl%2Fplayback%2Fpresentation%2F2.3%2F86cbb5c36361c9471658fc29134a603ab1b0ad30-1767824062525"
            },
            {
                "name": "Presentation\nAula virtual en vivo M贸dulo 2  Acceso a clases sincr贸nicasTe acercamos el enlace que utilizar...\nHover over an image to view it in full size\nWed, 7 Jan 2026, 8:14 PM -03 40",
                "type": "Presentation",
                "playback_link": "https://auladigital.sence.cl/mod/bigbluebuttonbn/bbb_view.php?action=play&bn=74528&mid=a268278243f16245a9538681a3a3ffdf76dfdcc4-5967-74528&rid=86cbb5c36361c9471658fc29134a603ab1b0ad30-1767827673987&rtype=presentation&href=https%3A%2F%2Faulavirtual.sence.cl%2Fplayback%2Fpresentation%2F2.3%2F86cbb5c36361c9471658fc29134a603ab1b0ad30-1767827673987"
            },
            {
                "name": "Presentation\nAula virtual en vivo M贸dulo 2  Acceso a clases sincr贸nicasTe acercamos el enlace que utilizar...\nHover over an image to view it in full size\nWed, 7 Jan 2026, 9:10 PM -03 50",
                "type": "Presentation",
                "playback_link": "https://auladigital.sence.cl/mod/bigbluebuttonbn/bbb_view.php?action=play&bn=74528&mid=a268278243f16245a9538681a3a3ffdf76dfdcc4-5967-74528&rid=86cbb5c36361c9471658fc29134a603ab1b0ad30-1767831041733&rtype=presentation&href=https%3A%2F%2Faulavirtual.sence.cl%2Fplayback%2Fpresentation%2F2.3%2F86cbb5c36361c9471658fc29134a603ab1b0ad30-1767831041733"
            },
            {
                "name": "Presentation\nAula virtual en vivo M贸dulo 2  Acceso a clases sincr贸nicasTe acercamos el enlace que utilizar...\nHover over an image to view it in full size\nThu, 8 Jan 2026, 5:54 PM -03 71",
                "type": "Presentation",
                "playback_link": "https://auladigital.sence.cl/mod/bigbluebuttonbn/bbb_view.php?action=play&bn=74528&mid=a268278243f16245a9538681a3a3ffdf76dfdcc4-5967-74528&rid=86cbb5c36361c9471658fc29134a603ab1b0ad30-1767905666111&rtype=presentation&href=https%3A%2F%2Faulavirtual.sence.cl%2Fplayback%2Fpresentation%2F2.3%2F86cbb5c36361c9471658fc29134a603ab1b0ad30-1767905666111"
            },
            {
                "name": "Presentation\nAula virtual en vivo M贸dulo 2  Acceso a clases sincr贸nicasTe acercamos el enlace que utilizar...\nHover over an image to view it in full size\nThu, 8 Jan 2026, 7:11 PM -03 38",
                "type": "Presentation",
                "playback_link": "https://auladigital.sence.cl/mod/bigbluebuttonbn/bbb_view.php?action=play&bn=74528&mid=a268278243f16245a9538681a3a3ffdf76dfdcc4-5967-74528&rid=86cbb5c36361c9471658fc29134a603ab1b0ad30-1767910305971&rtype=presentation&href=https%3A%2F%2Faulavirtual.sence.cl%2Fplayback%2Fpresentation%2F2.3%2F86cbb5c36361c9471658fc29134a603ab1b0ad30-1767910305971"
            },
            {
                "name": "Presentation\nAula virtual en vivo M贸dulo 2  Acceso a clases sincr贸nicasTe acercamos el enlace que utilizar...\nHover over an image to view it in full size\nThu, 8 Jan 2026, 8:10 PM -03 125",
                "type": "Presentation",
                "playback_link": "https://auladigital.sence.cl/mod/bigbluebuttonbn/bbb_view.php?action=play&bn=74528&mid=a268278243f16245a9538681a3a3ffdf76dfdcc4-5967-74528&rid=86cbb5c36361c9471658fc29134a603ab1b0ad30-1767913813897&rtype=presentation&href=https%3A%2F%2Faulavirtual.sence.cl%2Fplayback%2Fpresentation%2F2.3%2F86cbb5c36361c9471658fc29134a603ab1b0ad30-1767913813897"
            },
            {
                "name": "Presentation\nAula virtual en vivo M贸dulo 2  Acceso a clases sincr贸nicasTe acercamos el enlace que utilizar...\nHover over an image to view it in full size\nFri, 9 Jan 2026, 6:00 PM -03 75",
                "type": "Presentation",
                "playback_link": "https://auladigital.sence.cl/mod/bigbluebuttonbn/bbb_view.php?action=play&bn=74528&mid=a268278243f16245a9538681a3a3ffdf76dfdcc4-5967-74528&rid=86cbb5c36361c9471658fc29134a603ab1b0ad30-1767992458661&rtype=presentation&href=https%3A%2F%2Faulavirtual.sence.cl%2Fplayback%2Fpresentation%2F2.3%2F86cbb5c36361c9471658fc29134a603ab1b0ad30-1767992458661"
            },
            {
                "name": "Presentation\nAula virtual en vivo M贸dulo 2  Acceso a clases sincr贸nicasTe acercamos el enlace que utilizar...\nHover over an image to view it in full size\nFri, 9 Jan 2026, 7:22 PM -03 78",
                "type": "Presentation",
                "playback_link": "https://auladigital.sence.cl/mod/bigbluebuttonbn/bbb_view.php?action=play&bn=74528&mid=a268278243f16245a9538681a3a3ffdf76dfdcc4-5967-74528&rid=86cbb5c36361c9471658fc29134a603ab1b0ad30-1767997342611&rtype=presentation&href=https%3A%2F%2Faulavirtual.sence.cl%2Fplayback%2Fpresentation%2F2.3%2F86cbb5c36361c9471658fc29134a603ab1b0ad30-1767997342611"
            },
            {
                "name": "Presentation\nAula virtual en vivo M贸dulo 2  Acceso a clases sincr贸nicasTe acercamos el enlace que utilizar...\nHover over an image to view it in full size\nFri, 9 Jan 2026, 8:48 PM -03 72",
                "type": "Presentation",
                "playback_link": "https://auladigital.sence.cl/mod/bigbluebuttonbn/bbb_view.php?action=play&bn=74528&mid=a268278243f16245a9538681a3a3ffdf76dfdcc4-5967-74528&rid=86cbb5c36361c9471658fc29134a603ab1b0ad30-1768002534032&rtype=presentation&href=https%3A%2F%2Faulavirtual.sence.cl%2Fplayback%2Fpresentation%2F2.3%2F86cbb5c36361c9471658fc29134a603ab1b0ad30-1768002534032"
            },
            {
                "name": "Presentation\nAula virtual en vivo M贸dulo 2  Acceso a clases sincr贸nicasTe acercamos el enlace que utilizar...\nHover over an image to view it in full size\nMon, 12 Jan 2026, 5:53 PM -03 68",
                "type": "Presentation",
                "playback_link": "https://auladigital.sence.cl/mod/bigbluebuttonbn/bbb_view.php?action=play&bn=74528&mid=a268278243f16245a9538681a3a3ffdf76dfdcc4-5967-74528&rid=86cbb5c36361c9471658fc29134a603ab1b0ad30-1768251181366&rtype=presentation&href=https%3A%2F%2Faulavirtual.sence.cl%2Fplayback%2Fpresentation%2F2.3%2F86cbb5c36361c9471658fc29134a603ab1b0ad30-1768251181366"
            },
            {
                "name": "Presentation\nAula virtual en vivo M贸dulo 2  Acceso a clases sincr贸nicasTe acercamos el enlace que utilizar...\nHover over an image to view it in full size\nMon, 12 Jan 2026, 7:06 PM -03 68",
                "type": "Presentation",
                "playback_link": "https://auladigital.sence.cl/mod/bigbluebuttonbn/bbb_view.php?action=play&bn=74528&mid=a268278243f16245a9538681a3a3ffdf76dfdcc4-5967-74528&rid=86cbb5c36361c9471658fc29134a603ab1b0ad30-1768255590347&rtype=presentation&href=https%3A%2F%2Faulavirtual.sence.cl%2Fplayback%2Fpresentation%2F2.3%2F86cbb5c36361c9471658fc29134a603ab1b0ad30-1768255590347"
            },
            {
                "name": "Presentation\nAula virtual en vivo M贸dulo 2  Acceso a clases sincr贸nicasTe acercamos el enlace que utilizar...\nHover over an image to view it in full size\nMon, 12 Jan 2026, 8:21 PM -03 98",
                "type": "Presentation",
                "playback_link": "https://auladigital.sence.cl/mod/bigbluebuttonbn/bbb_view.php?action=play&bn=74528&mid=a268278243f16245a9538681a3a3ffdf76dfdcc4-5967-74528&rid=86cbb5c36361c9471658fc29134a603ab1b0ad30-1768260113835&rtype=presentation&href=https%3A%2F%2Faulavirtual.sence.cl%2Fplayback%2Fpresentation%2F2.3%2F86cbb5c36361c9471658fc29134a603ab1b0ad30-1768260113835"
            },
            {
                "name": "Presentation\nAula virtual en vivo M贸dulo 2  Acceso a clases sincr贸nicasTe acercamos el enlace que utilizar...\nHover over an image to view it in full size\nTue, 13 Jan 2026, 5:54 PM -03 77",
                "type": "Presentation",
                "playback_link": "https://auladigital.sence.cl/mod/bigbluebuttonbn/bbb_view.php?action=play&bn=74528&mid=a268278243f16245a9538681a3a3ffdf76dfdcc4-5967-74528&rid=86cbb5c36361c9471658fc29134a603ab1b0ad30-1768337697894&rtype=presentation&href=https%3A%2F%2Faulavirtual.sence.cl%2Fplayback%2Fpresentation%2F2.3%2F86cbb5c36361c9471658fc29134a603ab1b0ad30-1768337697894"
            },
            {
                "name": "Presentation\nAula virtual en vivo M贸dulo 2  Acceso a clases sincr贸nicasTe acercamos el enlace que utilizar...\nHover over an image to view it in full size\nTue, 13 Jan 2026, 7:15 PM -03 51",
                "type": "Presentation",
                "playback_link": "https://auladigital.sence.cl/mod/bigbluebuttonbn/bbb_view.php?action=play&bn=74528&mid=a268278243f16245a9538681a3a3ffdf76dfdcc4-5967-74528&rid=86cbb5c36361c9471658fc29134a603ab1b0ad30-1768342504845&rtype=presentation&href=https%3A%2F%2Faulavirtual.sence.cl%2Fplayback%2Fpresentation%2F2.3%2F86cbb5c36361c9471658fc29134a603ab1b0ad30-1768342504845"
            },
            {
                "name": "Presentation\nAula virtual en vivo M贸dulo 2  Acceso a clases sincr贸nicasTe acercamos el enlace que utilizar...\nHover over an image to view it in full size\nTue, 13 Jan 2026, 8:09 PM -03 70",
                "type": "Presentation",
                "playback_link": "https://auladigital.sence.cl/mod/bigbluebuttonbn/bbb_view.php?action=play&bn=74528&mid=a268278243f16245a9538681a3a3ffdf76dfdcc4-5967-74528&rid=86cbb5c36361c9471658fc29134a603ab1b0ad30-1768345798492&rtype=presentation&href=https%3A%2F%2Faulavirtual.sence.cl%2Fplayback%2Fpresentation%2F2.3%2F86cbb5c36361c9471658fc29134a603ab1b0ad30-1768345798492"
            },
            {
                "name": "Presentation\nAula virtual en vivo M贸dulo 2  Acceso a clases sincr贸nicasTe acercamos el enlace que utilizar...\nHover over an image to view it in full size\nTue, 13 Jan 2026, 9:21 PM -03 40",
                "type": "Presentation",
                "playback_link": "https://auladigital.sence.cl/mod/bigbluebuttonbn/bbb_view.php?action=play&bn=74528&mid=a268278243f16245a9538681a3a3ffdf76dfdcc4-5967-74528&rid=86cbb5c36361c9471658fc29134a603ab1b0ad30-1768350100833&rtype=presentation&href=https%3A%2F%2Faulavirtual.sence.cl%2Fplayback%2Fpresentation%2F2.3%2F86cbb5c36361c9471658fc29134a603ab1b0ad30-1768350100833"
            },
            {
                "name": "Presentation\nAula virtual en vivo M贸dulo 2  Acceso a clases sincr贸nicasTe acercamos el enlace que utilizar...\nHover over an image to view it in full size\nWed, 14 Jan 2026, 5:55 PM -03 72",
                "type": "Presentation",
                "playback_link": "https://auladigital.sence.cl/mod/bigbluebuttonbn/bbb_view.php?action=play&bn=74528&mid=a268278243f16245a9538681a3a3ffdf76dfdcc4-5967-74528&rid=86cbb5c36361c9471658fc29134a603ab1b0ad30-1768424127519&rtype=presentation&href=https%3A%2F%2Faulavirtual.sence.cl%2Fplayback%2Fpresentation%2F2.3%2F86cbb5c36361c9471658fc29134a603ab1b0ad30-1768424127519"
            },
            {
                "name": "Presentation\nAula virtual en vivo M贸dulo 2  Acceso a clases sincr贸nicasTe acercamos el enlace que utilizar...\nHover over an image to view it in full size\nWed, 14 Jan 2026, 7:10 PM -03 54",
                "type": "Presentation",
                "playback_link": "https://auladigital.sence.cl/mod/bigbluebuttonbn/bbb_view.php?action=play&bn=74528&mid=a268278243f16245a9538681a3a3ffdf76dfdcc4-5967-74528&rid=86cbb5c36361c9471658fc29134a603ab1b0ad30-1768428641223&rtype=presentation&href=https%3A%2F%2Faulavirtual.sence.cl%2Fplayback%2Fpresentation%2F2.3%2F86cbb5c36361c9471658fc29134a603ab1b0ad30-1768428641223"
            },
            {
                "name": "Presentation\nAula virtual en vivo M贸dulo 2  Acceso a clases sincr贸nicasTe acercamos el enlace que utilizar...\nHover over an image to view it in full size\nWed, 14 Jan 2026, 8:07 PM -03 74",
                "type": "Presentation",
                "playback_link": "https://auladigital.sence.cl/mod/bigbluebuttonbn/bbb_view.php?action=play&bn=74528&mid=a268278243f16245a9538681a3a3ffdf76dfdcc4-5967-74528&rid=86cbb5c36361c9471658fc29134a603ab1b0ad30-1768432047455&rtype=presentation&href=https%3A%2F%2Faulavirtual.sence.cl%2Fplayback%2Fpresentation%2F2.3%2F86cbb5c36361c9471658fc29134a603ab1b0ad30-1768432047455"
            },
            {
                "name": "Presentation\nAula virtual en vivo M贸dulo 2  Acceso a clases sincr贸nicasTe acercamos el enlace que utilizar...\nHover over an image to view it in full size\nWed, 14 Jan 2026, 9:23 PM -03 36",
                "type": "Presentation",
                "playback_link": "https://auladigital.sence.cl/mod/bigbluebuttonbn/bbb_view.php?action=play&bn=74528&mid=a268278243f16245a9538681a3a3ffdf76dfdcc4-5967-74528&rid=86cbb5c36361c9471658fc29134a603ab1b0ad30-1768436633673&rtype=presentation&href=https%3A%2F%2Faulavirtual.sence.cl%2Fplayback%2Fpresentation%2F2.3%2F86cbb5c36361c9471658fc29134a603ab1b0ad30-1768436633673"
            },
            {
                "name": "Presentation\nAula virtual en vivo M贸dulo 2  Acceso a clases sincr贸nicasTe acercamos el enlace que utilizar...\nHover over an image to view it in full size\nThu, 15 Jan 2026, 5:57 PM -03 70",
                "type": "Presentation",
                "playback_link": "https://auladigital.sence.cl/mod/bigbluebuttonbn/bbb_view.php?action=play&bn=74528&mid=a268278243f16245a9538681a3a3ffdf76dfdcc4-5967-74528&rid=86cbb5c36361c9471658fc29134a603ab1b0ad30-1768510652190&rtype=presentation&href=https%3A%2F%2Faulavirtual.sence.cl%2Fplayback%2Fpresentation%2F2.3%2F86cbb5c36361c9471658fc29134a603ab1b0ad30-1768510652190"
            },
            {
                "name": "Presentation\nAula virtual en vivo M贸dulo 2  Acceso a clases sincr贸nicasTe acercamos el enlace que utilizar...\nHover over an image to view it in full size\nThu, 15 Jan 2026, 7:10 PM -03 57",
                "type": "Presentation",
                "playback_link": "https://auladigital.sence.cl/mod/bigbluebuttonbn/bbb_view.php?action=play&bn=74528&mid=a268278243f16245a9538681a3a3ffdf76dfdcc4-5967-74528&rid=86cbb5c36361c9471658fc29134a603ab1b0ad30-1768515055034&rtype=presentation&href=https%3A%2F%2Faulavirtual.sence.cl%2Fplayback%2Fpresentation%2F2.3%2F86cbb5c36361c9471658fc29134a603ab1b0ad30-1768515055034"
            },
            {
                "name": "Presentation\nAula virtual en vivo M贸dulo 2  Acceso a clases sincr贸nicasTe acercamos el enlace que utilizar...\nHover over an image to view it in full size\nThu, 15 Jan 2026, 8:14 PM -03 103",
                "type": "Presentation",
                "playback_link": "https://auladigital.sence.cl/mod/bigbluebuttonbn/bbb_view.php?action=play&bn=74528&mid=a268278243f16245a9538681a3a3ffdf76dfdcc4-5967-74528&rid=86cbb5c36361c9471658fc29134a603ab1b0ad30-1768518888654&rtype=presentation&href=https%3A%2F%2Faulavirtual.sence.cl%2Fplayback%2Fpresentation%2F2.3%2F86cbb5c36361c9471658fc29134a603ab1b0ad30-1768518888654"
            },
            {
                "name": "Presentation\nAula virtual en vivo M贸dulo 2  Acceso a clases sincr贸nicasTe acercamos el enlace que utilizar...\nHover over an image to view it in full size\nFri, 16 Jan 2026, 5:58 PM -03 68",
                "type": "Presentation",
                "playback_link": "https://auladigital.sence.cl/mod/bigbluebuttonbn/bbb_view.php?action=play&bn=74528&mid=a268278243f16245a9538681a3a3ffdf76dfdcc4-5967-74528&rid=86cbb5c36361c9471658fc29134a603ab1b0ad30-1768597104918&rtype=presentation&href=https%3A%2F%2Faulavirtual.sence.cl%2Fplayback%2Fpresentation%2F2.3%2F86cbb5c36361c9471658fc29134a603ab1b0ad30-1768597104918"
            },
            {
                "name": "Presentation\nAula virtual en vivo M贸dulo 2  Acceso a clases sincr贸nicasTe acercamos el enlace que utilizar...\nHover over an image to view it in full size\nFri, 16 Jan 2026, 7:12 PM -03 57",
                "type": "Presentation",
                "playback_link": "https://auladigital.sence.cl/mod/bigbluebuttonbn/bbb_view.php?action=play&bn=74528&mid=a268278243f16245a9538681a3a3ffdf76dfdcc4-5967-74528&rid=86cbb5c36361c9471658fc29134a603ab1b0ad30-1768601549671&rtype=presentation&href=https%3A%2F%2Faulavirtual.sence.cl%2Fplayback%2Fpresentation%2F2.3%2F86cbb5c36361c9471658fc29134a603ab1b0ad30-1768601549671"
            },
            {
                "name": "Presentation\nAula virtual en vivo M贸dulo 2  Acceso a clases sincr贸nicasTe acercamos el enlace que utilizar...\nHover over an image to view it in full size\nFri, 16 Jan 2026, 8:12 PM -03 97",
                "type": "Presentation",
                "playback_link": "https://auladigital.sence.cl/mod/bigbluebuttonbn/bbb_view.php?action=play&bn=74528&mid=a268278243f16245a9538681a3a3ffdf76dfdcc4-5967-74528&rid=86cbb5c36361c9471658fc29134a603ab1b0ad30-1768605142254&rtype=presentation&href=https%3A%2F%2Faulavirtual.sence.cl%2Fplayback%2Fpresentation%2F2.3%2F86cbb5c36361c9471658fc29134a603ab1b0ad30-1768605142254"
            },
            {
                "name": "Presentation\nAula virtual en vivo M贸dulo 2  Acceso a clases sincr贸nicasTe acercamos el enlace que utilizar...\nHover over an image to view it in full size\nMon, 19 Jan 2026, 5:57 PM -03 64",
                "type": "Presentation",
                "playback_link": "https://auladigital.sence.cl/mod/bigbluebuttonbn/bbb_view.php?action=play&bn=74528&mid=a268278243f16245a9538681a3a3ffdf76dfdcc4-5967-74528&rid=86cbb5c36361c9471658fc29134a603ab1b0ad30-1768856225628&rtype=presentation&href=https%3A%2F%2Faulavirtual.sence.cl%2Fplayback%2Fpresentation%2F2.3%2F86cbb5c36361c9471658fc29134a603ab1b0ad30-1768856225628"
            },
            {
                "name": "Presentation\nAula virtual en vivo M贸dulo 2  Acceso a clases sincr贸nicasTe acercamos el enlace que utilizar...\nHover over an image to view it in full size\nMon, 19 Jan 2026, 7:03 PM -03 71",
                "type": "Presentation",
                "playback_link": "https://auladigital.sence.cl/mod/bigbluebuttonbn/bbb_view.php?action=play&bn=74528&mid=a268278243f16245a9538681a3a3ffdf76dfdcc4-5967-74528&rid=86cbb5c36361c9471658fc29134a603ab1b0ad30-1768860233157&rtype=presentation&href=https%3A%2F%2Faulavirtual.sence.cl%2Fplayback%2Fpresentation%2F2.3%2F86cbb5c36361c9471658fc29134a603ab1b0ad30-1768860233157"
            },
            {
                "name": "Presentation\nAula virtual en vivo M贸dulo 2  Acceso a clases sincr贸nicasTe acercamos el enlace que utilizar...\nHover over an image to view it in full size\nMon, 19 Jan 2026, 8:23 PM -03 113",
                "type": "Presentation",
                "playback_link": "https://auladigital.sence.cl/mod/bigbluebuttonbn/bbb_view.php?action=play&bn=74528&mid=a268278243f16245a9538681a3a3ffdf76dfdcc4-5967-74528&rid=86cbb5c36361c9471658fc29134a603ab1b0ad30-1768865025612&rtype=presentation&href=https%3A%2F%2Faulavirtual.sence.cl%2Fplayback%2Fpresentation%2F2.3%2F86cbb5c36361c9471658fc29134a603ab1b0ad30-1768865025612"
            },
            {
                "name": "Presentation\nAula virtual en vivo M贸dulo 2  Acceso a clases sincr贸nicasTe acercamos el enlace que utilizar...\nHover over an image to view it in full size\nTue, 20 Jan 2026, 5:48 PM -03 71",
                "type": "Presentation",
                "playback_link": "https://auladigital.sence.cl/mod/bigbluebuttonbn/bbb_view.php?action=play&bn=74528&mid=a268278243f16245a9538681a3a3ffdf76dfdcc4-5967-74528&rid=86cbb5c36361c9471658fc29134a603ab1b0ad30-1768942109783&rtype=presentation&href=https%3A%2F%2Faulavirtual.sence.cl%2Fplayback%2Fpresentation%2F2.3%2F86cbb5c36361c9471658fc29134a603ab1b0ad30-1768942109783"
            },
            {
                "name": "Presentation\nAula virtual en vivo M贸dulo 2  Acceso a clases sincr贸nicasTe acercamos el enlace que utilizar...\nHover over an image to view it in full size\nTue, 20 Jan 2026, 7:10 PM -03 57",
                "type": "Presentation",
                "playback_link": "https://auladigital.sence.cl/mod/bigbluebuttonbn/bbb_view.php?action=play&bn=74528&mid=a268278243f16245a9538681a3a3ffdf76dfdcc4-5967-74528&rid=86cbb5c36361c9471658fc29134a603ab1b0ad30-1768947009635&rtype=presentation&href=https%3A%2F%2Faulavirtual.sence.cl%2Fplayback%2Fpresentation%2F2.3%2F86cbb5c36361c9471658fc29134a603ab1b0ad30-1768947009635"
            },
            {
                "name": "Presentation\nAula virtual en vivo M贸dulo 2  Acceso a clases sincr贸nicasTe acercamos el enlace que utilizar...\nHover over an image to view it in full size\nTue, 20 Jan 2026, 8:09 PM -03 104",
                "type": "Presentation",
                "playback_link": "https://auladigital.sence.cl/mod/bigbluebuttonbn/bbb_view.php?action=play&bn=74528&mid=a268278243f16245a9538681a3a3ffdf76dfdcc4-5967-74528&rid=86cbb5c36361c9471658fc29134a603ab1b0ad30-1768950578385&rtype=presentation&href=https%3A%2F%2Faulavirtual.sence.cl%2Fplayback%2Fpresentation%2F2.3%2F86cbb5c36361c9471658fc29134a603ab1b0ad30-1768950578385"
            }
        ]
    }
}